[
    {
        "speaker": "caller",
        "text": "then in emergency with your grand on any the in the hospital and we need you to send money right away",
        "timestamp": "2024-03-09 18:17:24"
    },
    {
        "speaker": "assistant",
        "text": "I'm sorry to hear about your emergency situation with your grandparent. In order to proceed, I will need to verify some information to ensure the legitimacy of the request. Can you please provide me with your full name and the hospital where your grandparent is receiving treatment?",
        "timestamp": "2024-03-09 18:17:26"
    }
]